LICENSE.md
README.md
setup.cfg
setup.py
teleout/__init__.py
teleout/main.py
teleout.egg-info/PKG-INFO
teleout.egg-info/SOURCES.txt
teleout.egg-info/dependency_links.txt
teleout.egg-info/entry_points.txt
teleout.egg-info/requires.txt
teleout.egg-info/top_level.txt