Metadata-Version: 2.1
Name: teleout
Version: 1.1.2
Summary: Terminal utility, for sending data directly to telegram users from bot via pipes, files or just text.
Home-page: https://github.com/TeaDove/teleout
Author: Peter Ibragimov
Author-email: peter.ibragimov@gmail.com
License: gpl-3.0
Download-URL: https://github.com/TeaDove/teleout/archive/v1.1.2.tar.gz
Keywords: TELEGRAM,PIPE,UTILITY
Platform: UNKNOWN
Classifier: Development Status :: 5 - Production/Stable
Classifier: Intended Audience :: Developers
Classifier: Environment :: Console
Classifier: Natural Language :: English
Classifier: Programming Language :: Python :: 3.7
Classifier: Programming Language :: Python :: 3.8
Classifier: License :: OSI Approved :: GNU General Public License v3 (GPLv3)
Classifier: Operating System :: Unix
Classifier: Topic :: Utilities
Requires-Python: >=3.7
License-File: LICENSE.md
